automvs/__init__.py
automvs-0.2.1.dist-info/LICENSE
automvs-0.2.1.dist-info/METADATA
automvs-0.2.1.dist-info/WHEEL
automvs-0.2.1.dist-info/top_level.txt
automvs-0.2.1.dist-info/RECORD
