Metadata-Version: 2.2
Name: automvs
Version: 0.2.1
Summary: Python library for MVS/CE automation
Home-page: https://github.com/MVS-sysgen/automvs
Author: Philip Young
Author-email: mainframed767@gmail.com
License: MIT
Classifier: Development Status :: 4 - Beta
Classifier: Intended Audience :: Science/Research
Classifier: License :: OSI Approved :: MIT License
Classifier: Programming Language :: Python :: 3
License-File: LICENSE
Dynamic: author
Dynamic: author-email
Dynamic: classifier
Dynamic: description
Dynamic: description-content-type
Dynamic: home-page
Dynamic: license
Dynamic: summary
